pyLJcrypt/__init__.py
pyLJcrypt-0.0.6.dist-info/METADATA
pyLJcrypt-0.0.6.dist-info/WHEEL
pyLJcrypt-0.0.6.dist-info/top_level.txt
pyLJcrypt-0.0.6.dist-info/RECORD
