Metadata-Version: 2.1
Name: pyLJcrypt
Version: 0.0.6
Summary: Making Encrypting and Decrypting easy.
Home-page: UNKNOWN
Author: Louiejay S. Boglosa
Author-email: boglosalouiejay@gmail.com
License: UNKNOWN
Keywords: python,cryptography,encrypting,decrypting
Platform: UNKNOWN
Classifier: Programming Language :: Python :: 3
Classifier: Operating System :: Unix
Classifier: Operating System :: MacOS :: MacOS X
Classifier: Operating System :: Microsoft :: Windows
Classifier: Operating System :: POSIX :: Linux
Requires-Dist: cryptography
